pystatacons/__init__.py
pystatacons/configuration.py
pystatacons/deciders.py
pystatacons/py.typed
pystatacons/special_sigs.py
pystatacons/stata_utils.py
pystatacons-3.0.4.dist-info/LICENSE
pystatacons-3.0.4.dist-info/METADATA
pystatacons-3.0.4.dist-info/WHEEL
pystatacons-3.0.4.dist-info/top_level.txt
pystatacons-3.0.4.dist-info/RECORD
