Metadata-Version: 2.1
Name: pystatacons
Version: 3.0.4
Summary: statacons Python package
Home-page: https://github.com/bquistorff/statacons
Author: Statacons team
Author-email: Brian.Quistorff@bea.gov
Requires-Python: >=3.5
License-File: LICENSE
Requires-Dist: scons
Requires-Dist: pywin32; sys_platform == "win32"
